hebill_multiple_settings/__init__.py
hebill_multiple_settings/common_settings.py
hebill_multiple_settings/multiple_settings.py
hebill_multiple_settings/package_settings.py
hebill_multiple_settings/user_settings.py
hebill_multiple_settings-1.0.0.dist-info/METADATA
hebill_multiple_settings-1.0.0.dist-info/WHEEL
hebill_multiple_settings-1.0.0.dist-info/top_level.txt
hebill_multiple_settings-1.0.0.dist-info/RECORD
