Metadata-Version: 2.1
Name: hebill-multiple-settings
Version: 1.0.0
Summary: Python Multiple Settings
Home-page: https://www.hebill.net/hebill_multiple_settings
Author: He Bill
Author-email: hebill@me.com
Requires-Python: >=3.11
